LICENSE
MANIFEST.in
README.md
requirements.txt
setup.cfg
setup.py
gpgpass/__init__.py
gpgpass/gpgpass.py
gpgpass.egg-info/PKG-INFO
gpgpass.egg-info/SOURCES.txt
gpgpass.egg-info/dependency_links.txt
gpgpass.egg-info/entry_points.txt
gpgpass.egg-info/requires.txt
gpgpass.egg-info/top_level.txt