Metadata-Version: 1.1
Name: gpgpass
Version: 0.1.3
Summary: Password manager for groups. Searching thru GPG-encrypted password files.
Home-page: https://github.com/rvdh/gpgpass
Author: Rick van den Hof
Author-email: r.vandenhof@tiw.nl
License: Apache License, Version 2.0
Keywords: python passwords security gpg git
Platform: UNKNOWN
Classifier: Intended Audience :: Developers
Classifier: Intended Audience :: System Administrators
Classifier: Topic :: Utilities
Classifier: Topic :: Security :: Cryptography
Classifier: Environment :: Console
Classifier: License :: OSI Approved :: Apache Software License
Classifier: Programming Language :: Python :: 2.7
Classifier: Operating System :: OS Independent
Classifier: Development Status :: 4 - Beta
